[
  {
    "id": 1,
    "description": null,
    "modifier": null,
    "dept_belong_id": null,
    "update_datetime": "2023-07-07 21:52:21.706323",
    "create_datetime": "2023-07-07 21:52:21.706344",
    "icon": "cog",
    "name": "系统管理",
    "sort": 1,
    "is_link": 0,
    "is_catalog": 1,
    "web_path": "",
    "component": "",
    "component_name": "",
    "status": 1,
    "cache": 0,
    "visible": 1,
    "creator_id": null,
    "parent_id": null,
    "is_deleted": 0
  },
  {
    "id": 2,
    "description": null,
    "modifier": null,
    "dept_belong_id": null,
    "update_datetime": "2023-07-07 21:52:21.734648",
    "create_datetime": "2023-07-07 21:52:21.734668",
    "icon": "navicon",
    "name": "菜单管理",
    "sort": 1,
    "is_link": 0,
    "is_catalog": 0,
    "web_path": "/menu",
    "component": "system/menu",
    "component_name": "menu",
    "status": 1,
    "cache": 0,
    "visible": 1,
    "creator_id": null,
    "parent_id": 1,
    "is_deleted": 0
  },
  {
    "id": 3,
    "description": null,
    "modifier": null,
    "dept_belong_id": null,
    "update_datetime": "2023-07-07 21:52:21.905985",
    "create_datetime": "2023-07-07 21:52:21.906000",
    "icon": "dot-circle-o",
    "name": "菜单按钮",
    "sort": 2,
    "is_link": 0,
    "is_catalog": 0,
    "web_path": "/menuButton",
    "component": "system/menuButton/index",
    "component_name": "menuButton",
    "status": 1,
    "cache": 0,
    "visible": 0,
    "creator_id": null,
    "parent_id": 1,
    "is_deleted": 0
  },
  {
    "id": 4,
    "description": null,
    "modifier": null,
    "dept_belong_id": null,
    "update_datetime": "2023-07-07 21:52:22.038755",
    "create_datetime": "2023-07-07 21:52:22.038773",
    "icon": "bank",
    "name": "部门管理",
    "sort": 3,
    "is_link": 0,
    "is_catalog": 0,
    "web_path": "/dept",
    "component": "system/dept/index",
    "component_name": "dept",
    "status": 1,
    "cache": 0,
    "visible": 1,
    "creator_id": null,
    "parent_id": 1,
    "is_deleted": 0
  },
  {
    "id": 5,
    "description": null,
    "modifier": null,
    "dept_belong_id": null,
    "update_datetime": "2023-07-07 21:52:22.200291",
    "create_datetime": "2023-07-07 21:52:22.200311",
    "icon": "address-book",
    "name": "角色管理",
    "sort": 4,
    "is_link": 0,
    "is_catalog": 0,
    "web_path": "/role",
    "component": "system/role/index",
    "component_name": "role",
    "status": 1,
    "cache": 0,
    "visible": 1,
    "creator_id": null,
    "parent_id": 1,
    "is_deleted": 0
  },
  {
    "id": 6,
    "description": null,
    "modifier": null,
    "dept_belong_id": null,
    "update_datetime": "2023-07-07 21:52:22.380738",
    "create_datetime": "2023-07-07 21:52:22.380756",
    "icon": "users",
    "name": "用户管理",
    "sort": 6,
    "is_link": 0,
    "is_catalog": 0,
    "web_path": "/user",
    "component": "system/user/index",
    "component_name": "user",
    "status": 1,
    "cache": 0,
    "visible": 1,
    "creator_id": null,
    "parent_id": 1,
    "is_deleted": 0
  },
  {
    "id": 7,
    "description": null,
    "modifier": null,
    "dept_belong_id": null,
    "update_datetime": "2023-07-07 21:52:22.648341",
    "create_datetime": "2023-07-07 21:52:22.648360",
    "icon": "bullhorn",
    "name": "消息中心",
    "sort": 7,
    "is_link": 0,
    "is_catalog": 0,
    "web_path": "/messageCenter",
    "component": "system/messageCenter/index",
    "component_name": "messageCenter",
    "status": 1,
    "cache": 0,
    "visible": 1,
    "creator_id": null,
    "parent_id": 1,
    "is_deleted": 0
  },
  {
    "id": 8,
    "description": null,
    "modifier": null,
    "dept_belong_id": null,
    "update_datetime": "2023-07-07 21:52:22.806564",
    "create_datetime": "2023-07-07 21:52:22.806580",
    "icon": "compass",
    "name": "接口白名单",
    "sort": 8,
    "is_link": 0,
    "is_catalog": 0,
    "web_path": "/apiWhiteList",
    "component": "system/whiteList/index",
    "component_name": "whiteList",
    "status": 1,
    "cache": 0,
    "visible": 1,
    "creator_id": null,
    "parent_id": 1,
    "is_deleted": 0
  },
  {
    "id": 9,
    "description": null,
    "modifier": null,
    "dept_belong_id": null,
    "update_datetime": "2023-07-07 21:52:22.964617",
    "create_datetime": "2023-07-07 21:52:22.964644",
    "icon": "cogs",
    "name": "常规配置",
    "sort": 2,
    "is_link": 0,
    "is_catalog": 1,
    "web_path": "",
    "component": "",
    "component_name": "",
    "status": 1,
    "cache": 0,
    "visible": 1,
    "creator_id": null,
    "parent_id": null,
    "is_deleted": 0
  },
  {
    "id": 10,
    "description": null,
    "modifier": null,
    "dept_belong_id": null,
    "update_datetime": "2023-07-07 21:52:22.992211",
    "create_datetime": "2023-07-07 21:52:22.992231",
    "icon": "desktop",
    "name": "系统配置",
    "sort": 0,
    "is_link": 0,
    "is_catalog": 0,
    "web_path": "/config",
    "component": "system/config/index",
    "component_name": "config",
    "status": 1,
    "cache": 0,
    "visible": 1,
    "creator_id": null,
    "parent_id": 9,
    "is_deleted": 0
  },
  {
    "id": 11,
    "description": null,
    "modifier": null,
    "dept_belong_id": null,
    "update_datetime": "2023-07-07 21:52:23.148320",
    "create_datetime": "2023-07-07 21:52:23.148336",
    "icon": "book",
    "name": "字典管理",
    "sort": 1,
    "is_link": 0,
    "is_catalog": 0,
    "web_path": "/dictionary",
    "component": "system/dictionary/index",
    "component_name": "dictionary",
    "status": 1,
    "cache": 0,
    "visible": 1,
    "creator_id": null,
    "parent_id": 9,
    "is_deleted": 0
  },
  {
    "id": 12,
    "description": null,
    "modifier": null,
    "dept_belong_id": null,
    "update_datetime": "2023-07-07 21:52:23.320782",
    "create_datetime": "2023-07-07 21:52:23.320800",
    "icon": "map",
    "name": "地区管理",
    "sort": 2,
    "is_link": 0,
    "is_catalog": 0,
    "web_path": "/areas",
    "component": "system/areas/index",
    "component_name": "areas",
    "status": 1,
    "cache": 0,
    "visible": 1,
    "creator_id": null,
    "parent_id": 9,
    "is_deleted": 0
  },
  {
    "id": 13,
    "description": null,
    "modifier": null,
    "dept_belong_id": null,
    "update_datetime": "2023-07-07 21:52:23.475296",
    "create_datetime": "2023-07-07 21:52:23.475315",
    "icon": "file-text-o",
    "name": "附件管理",
    "sort": 3,
    "is_link": 0,
    "is_catalog": 0,
    "web_path": "/file",
    "component": "system/fileList/index",
    "component_name": "file",
    "status": 1,
    "cache": 0,
    "visible": 1,
    "creator_id": null,
    "parent_id": 9,
    "is_deleted": 0
  },
  {
    "id": 14,
    "description": null,
    "modifier": null,
    "dept_belong_id": null,
    "update_datetime": "2023-07-07 21:52:23.610352",
    "create_datetime": "2023-07-07 21:52:23.610374",
    "icon": "book",
    "name": "日志管理",
    "sort": 3,
    "is_link": 0,
    "is_catalog": 1,
    "web_path": "",
    "component": "",
    "component_name": "",
    "status": 1,
    "cache": 0,
    "visible": 1,
    "creator_id": null,
    "parent_id": null,
    "is_deleted": 0
  },
  {
    "id": 15,
    "description": null,
    "modifier": null,
    "dept_belong_id": null,
    "update_datetime": "2023-07-07 21:52:23.636609",
    "create_datetime": "2023-07-07 21:52:23.636627",
    "icon": "file-text",
    "name": "登录日志",
    "sort": 1,
    "is_link": 0,
    "is_catalog": 0,
    "web_path": "/loginLog",
    "component": "system/log/loginLog/index",
    "component_name": "loginLog",
    "status": 1,
    "cache": 0,
    "visible": 1,
    "creator_id": null,
    "parent_id": 14,
    "is_deleted": 0
  },
  {
    "id": 16,
    "description": null,
    "modifier": null,
    "dept_belong_id": null,
    "update_datetime": "2023-07-07 21:52:23.716248",
    "create_datetime": "2023-07-07 21:52:23.716268",
    "icon": "file-code-o",
    "name": "操作日志",
    "sort": 2,
    "is_link": 0,
    "is_catalog": 0,
    "web_path": "/operationLog",
    "component": "system/log/operationLog/index",
    "component_name": "operationLog",
    "status": 1,
    "cache": 0,
    "visible": 1,
    "creator_id": null,
    "parent_id": 14,
    "is_deleted": 0
  },
  {
    "id": 19,
    "description": "",
    "modifier": "1",
    "dept_belong_id": "1",
    "update_datetime": "2023-07-10 21:02:47.526006",
    "create_datetime": "2023-07-10 20:59:55.236024",
    "icon": "pied-piper-pp",
    "name": "会员管理",
    "sort": 1,
    "is_link": 0,
    "is_catalog": 1,
    "web_path": "",
    "component": "",
    "component_name": "",
    "status": 1,
    "cache": 0,
    "visible": 1,
    "creator_id": 1,
    "parent_id": null,
    "is_deleted": 0
  },
  {
    "id": 20,
    "description": null,
    "modifier": "1",
    "dept_belong_id": "1",
    "update_datetime": "2023-07-10 21:13:44.502229",
    "create_datetime": "2023-07-10 21:13:44.502248",
    "icon": "linux",
    "name": "会员列表",
    "sort": 1,
    "is_link": 0,
    "is_catalog": 0,
    "web_path": "/members",
    "component": "members/member/index",
    "component_name": "member",
    "status": 1,
    "cache": 0,
    "visible": 1,
    "creator_id": 1,
    "parent_id": 19,
    "is_deleted": 0
  },
  {
    "id": 21,
    "description": "",
    "modifier": "1",
    "dept_belong_id": "1",
    "update_datetime": "2023-08-07 15:06:03.330968",
    "create_datetime": "2023-08-02 20:26:38.470050",
    "icon": "product-hunt",
    "name": "VIP商品",
    "sort": 2,
    "is_link": 0,
    "is_catalog": 0,
    "web_path": "/vip",
    "component": "members/vip/index",
    "component_name": "vip",
    "status": 1,
    "cache": 0,
    "visible": 1,
    "creator_id": 1,
    "parent_id": 19,
    "is_deleted": 0
  },
  {
    "id": 22,
    "description": null,
    "modifier": "1",
    "dept_belong_id": "1",
    "update_datetime": "2023-08-07 16:56:33.154555",
    "create_datetime": "2023-08-07 16:56:33.154574",
    "icon": "bandcamp",
    "name": "用户会员",
    "sort": 3,
    "is_link": 0,
    "is_catalog": 0,
    "web_path": "/user-vip",
    "component": "members/userVip/index",
    "component_name": "userVip",
    "status": 1,
    "cache": 0,
    "visible": 1,
    "creator_id": 1,
    "parent_id": 19,
    "is_deleted": 0
  },
  {
    "id": 23,
    "description": null,
    "modifier": "1",
    "dept_belong_id": "1",
    "update_datetime": "2023-08-07 19:51:43.376332",
    "create_datetime": "2023-08-07 19:51:43.376354",
    "icon": "instagram",
    "name": "用户地址",
    "sort": 1,
    "is_link": 0,
    "is_catalog": 0,
    "web_path": "/user-addr",
    "component": "members/addr/index",
    "component_name": "addr",
    "status": 1,
    "cache": 0,
    "visible": 1,
    "creator_id": 1,
    "parent_id": 19,
    "is_deleted": 0
  },
  {
    "id": 24,
    "description": null,
    "modifier": "1",
    "dept_belong_id": "1",
    "update_datetime": "2023-08-09 17:42:57.810407",
    "create_datetime": "2023-08-09 17:42:57.810425",
    "icon": "buysellads",
    "name": "广告配置",
    "sort": 3,
    "is_link": 0,
    "is_catalog": 1,
    "web_path": null,
    "component": null,
    "component_name": null,
    "status": 1,
    "cache": 0,
    "visible": 1,
    "creator_id": 1,
    "parent_id": null,
    "is_deleted": 0
  },
  {
    "id": 25,
    "description": null,
    "modifier": "1",
    "dept_belong_id": "1",
    "update_datetime": "2023-08-09 17:43:47.915696",
    "create_datetime": "2023-08-09 17:43:47.915714",
    "icon": "file-image-o",
    "name": "轮播图",
    "sort": 1,
    "is_link": 0,
    "is_catalog": 0,
    "web_path": "/banners",
    "component": "advertise/banners/index",
    "component_name": "banners",
    "status": 1,
    "cache": 0,
    "visible": 1,
    "creator_id": 1,
    "parent_id": 24,
    "is_deleted": 0
  },
  {
    "id": 26,
    "description": null,
    "modifier": "1",
    "dept_belong_id": "1",
    "update_datetime": "2023-08-09 19:53:18.681288",
    "create_datetime": "2023-08-09 19:53:18.681306",
    "icon": "file-code-o",
    "name": "公告配置",
    "sort": 2,
    "is_link": 0,
    "is_catalog": 0,
    "web_path": "/notice",
    "component": "advertise/notice/index",
    "component_name": "notice",
    "status": 1,
    "cache": 0,
    "visible": 1,
    "creator_id": 1,
    "parent_id": 24,
    "is_deleted": 0
  },
  {
    "id": 27,
    "description": null,
    "modifier": "1",
    "dept_belong_id": "1",
    "update_datetime": "2023-08-09 19:54:53.656284",
    "create_datetime": "2023-08-09 19:54:53.656301",
    "icon": "align-center",
    "name": "跑马灯",
    "sort": 3,
    "is_link": 0,
    "is_catalog": 0,
    "web_path": "/marquee",
    "component": "advertise/marquee/index",
    "component_name": "marquee",
    "status": 1,
    "cache": 0,
    "visible": 1,
    "creator_id": 1,
    "parent_id": 24,
    "is_deleted": 0
  },
  {
    "id": 28,
    "description": null,
    "modifier": "1",
    "dept_belong_id": "1",
    "update_datetime": "2023-08-11 11:41:21.273905",
    "create_datetime": "2023-08-10 11:54:14.792115",
    "icon": "arrow-circle-o-up",
    "name": "服务项目",
    "sort": 2,
    "is_link": 0,
    "is_catalog": 1,
    "web_path": "",
    "component": "",
    "component_name": "",
    "status": 1,
    "cache": 0,
    "visible": 1,
    "creator_id": 1,
    "parent_id": null,
    "is_deleted": 0
  },
  {
    "id": 29,
    "description": null,
    "modifier": "1",
    "dept_belong_id": "1",
    "update_datetime": "2023-08-10 11:56:32.868578",
    "create_datetime": "2023-08-10 11:56:32.868596",
    "icon": "product-hunt",
    "name": "基础项目",
    "sort": 1,
    "is_link": 0,
    "is_catalog": 0,
    "web_path": "/project",
    "component": "projects/project/index",
    "component_name": "project",
    "status": 1,
    "cache": 0,
    "visible": 1,
    "creator_id": 1,
    "parent_id": 28,
    "is_deleted": 0
  },
  {
    "id": 30,
    "description": null,
    "modifier": "1",
    "dept_belong_id": "1",
    "update_datetime": "2023-08-10 16:08:37.151661",
    "create_datetime": "2023-08-10 16:08:37.151680",
    "icon": "xing-square",
    "name": "师傅管理",
    "sort": 2,
    "is_link": 0,
    "is_catalog": 1,
    "web_path": null,
    "component": null,
    "component_name": null,
    "status": 1,
    "cache": 0,
    "visible": 1,
    "creator_id": 1,
    "parent_id": null,
    "is_deleted": 0
  },
  {
    "id": 31,
    "description": "",
    "modifier": "1",
    "dept_belong_id": "1",
    "update_datetime": "2023-08-10 16:33:51.486169",
    "create_datetime": "2023-08-10 16:09:48.765216",
    "icon": "adn",
    "name": "入住申请",
    "sort": 1,
    "is_link": 0,
    "is_catalog": 0,
    "web_path": "/master-check-in",
    "component": "masters/masterCheckIn/index",
    "component_name": "masterCheckIn",
    "status": 1,
    "cache": 0,
    "visible": 1,
    "creator_id": 1,
    "parent_id": 30,
    "is_deleted": 0
  },
  {
    "id": 32,
    "description": null,
    "modifier": "1",
    "dept_belong_id": "1",
    "update_datetime": "2023-08-10 16:59:03.413456",
    "create_datetime": "2023-08-10 16:59:03.413477",
    "icon": "500px",
    "name": "师傅列表",
    "sort": 2,
    "is_link": 0,
    "is_catalog": 0,
    "web_path": "/master",
    "component": "masters/master/index",
    "component_name": "master",
    "status": 1,
    "cache": 0,
    "visible": 1,
    "creator_id": 1,
    "parent_id": 30,
    "is_deleted": 0
  },
  {
    "id": 33,
    "description": null,
    "modifier": "1",
    "dept_belong_id": "1",
    "update_datetime": "2023-08-11 11:41:51.784306",
    "create_datetime": "2023-08-11 11:41:51.784323",
    "icon": "cc-paypal",
    "name": "财务管理",
    "sort": 2,
    "is_link": 0,
    "is_catalog": 1,
    "web_path": null,
    "component": null,
    "component_name": null,
    "status": 1,
    "cache": 0,
    "visible": 1,
    "creator_id": 1,
    "parent_id": null,
    "is_deleted": 0
  },
  {
    "id": 34,
    "description": null,
    "modifier": "1",
    "dept_belong_id": "1",
    "update_datetime": "2023-08-11 11:42:47.171275",
    "create_datetime": "2023-08-11 11:42:47.171290",
    "icon": "paypal",
    "name": "支付渠道",
    "sort": 1,
    "is_link": 0,
    "is_catalog": 0,
    "web_path": "/pay-channel",
    "component": "finance/payChannel/index",
    "component_name": "payChannel",
    "status": 1,
    "cache": 0,
    "visible": 1,
    "creator_id": 1,
    "parent_id": 33,
    "is_deleted": 0
  },
  {
    "id": 35,
    "description": null,
    "modifier": "1",
    "dept_belong_id": "1",
    "update_datetime": "2023-08-11 12:03:55.426938",
    "create_datetime": "2023-08-11 12:03:55.426958",
    "icon": "reorder",
    "name": "订单管理",
    "sort": 6,
    "is_link": 0,
    "is_catalog": 1,
    "web_path": null,
    "component": null,
    "component_name": null,
    "status": 1,
    "cache": 0,
    "visible": 1,
    "creator_id": 1,
    "parent_id": null,
    "is_deleted": 0
  },
  {
    "id": 36,
    "description": null,
    "modifier": "1",
    "dept_belong_id": "1",
    "update_datetime": "2023-08-11 12:06:02.795918",
    "create_datetime": "2023-08-11 12:06:02.795937",
    "icon": "first-order",
    "name": "服务订单",
    "sort": 1,
    "is_link": 0,
    "is_catalog": 0,
    "web_path": "/service-order",
    "component": "orders/serviceOrder/index",
    "component_name": "serviceOrder",
    "status": 1,
    "cache": 0,
    "visible": 1,
    "creator_id": 1,
    "parent_id": 35,
    "is_deleted": 0
  },
  {
    "id": 37,
    "description": null,
    "modifier": "1",
    "dept_belong_id": "1",
    "update_datetime": "2023-08-11 15:46:35.944987",
    "create_datetime": "2023-08-11 15:46:35.945004",
    "icon": "cc-paypal",
    "name": "支付订单",
    "sort": 2,
    "is_link": 0,
    "is_catalog": 0,
    "web_path": "/pay-order",
    "component": "orders/payOrder/index",
    "component_name": "payOrder",
    "status": 1,
    "cache": 0,
    "visible": 1,
    "creator_id": 1,
    "parent_id": 35,
    "is_deleted": 0
  },
  {
    "id": 38,
    "description": null,
    "modifier": "1",
    "dept_belong_id": "1",
    "update_datetime": "2023-08-11 20:13:21.399805",
    "create_datetime": "2023-08-11 20:09:23.947346",
    "icon": "motorcycle",
    "name": "技师服务项目",
    "sort": 2,
    "is_link": 0,
    "is_catalog": 0,
    "web_path": "/master-project",
    "component": "projects/masterProject/index",
    "component_name": "masterProject",
    "status": 1,
    "cache": 0,
    "visible": 1,
    "creator_id": 1,
    "parent_id": 28,
    "is_deleted": 0
  }
]
